{"variables":{"3357":{"years":[],"entities":[],"values":[],"id":3357,"name":"Contraceptive prevalence, modern methods (% of women ages 15-49)","unit":"% of women ages 15-49","description":"Contraceptive prevalence rate is the percentage of women who are practicing, or whose sexual partners are practicing, at least one modern method of contraception. It is usually measured for women ages 15-49 who are married or in union. Modern methods of contraception include female and male sterilization, oral hormonal pills, the intra-uterine device (IUD), the male condom, injectables, the implant (including Norplant), vaginal barrier methods, the female condom and emergency contraception.","created_at":"2017-07-06T13:03:31.000Z","updated_at":"2018-02-28T13:58:31.000Z","uploaded_at":"2017-07-06T13:03:31.000Z","code":"SP.DYN.CONM.ZS","coverage":"","timespan":"1960-2016","datasetId":563,"variableTypeId":4,"sourceId":2019,"uploaded_by":null,"display":{},"shortUnit":"%","datasetName":"World Development Indicators - Health","s_id":2019,"s_name":"World Bank – WDI: Contraceptive prevalence, modern methods (% of women ages 15-49)","source":{"id":2019,"name":"World Bank – WDI: Contraceptive prevalence, modern methods (% of women ages 15-49)","dataPublishedBy":"World Bank – World Development Indicators","dataPublisherSource":"Household surveys, including Demographic and Health Surveys and Multiple Indicator Cluster Surveys. Largely compiled by United Nations Population Division.","link":"http://data.worldbank.org/data-catalog/world-development-indicators","retrievedData":"","additionalInfo":""}}},"entityKey":{}}